edafa/BasePredictor.py
edafa/ClassPredictor.py
edafa/SegPredictor.py
edafa/__init__.py
edafa/exceptions.py
edafa/utils.py
edafa-0.1.5.dist-info/LICENSE
edafa-0.1.5.dist-info/METADATA
edafa-0.1.5.dist-info/WHEEL
edafa-0.1.5.dist-info/top_level.txt
edafa-0.1.5.dist-info/RECORD
