Metadata-Version: 2.1
Name: edafa
Version: 0.1.5
Summary: Test Time Augmentation (TTA) wrapper for computer vision tasks: segmentation,classification, super-resolution, ... etc.
Home-page: https://github.com/andrewekhalel/edafa
Author: Andrew Khalel
Author-email: andrewekhalel@gmail.com
License: MIT
Keywords: augmentation classification segmentation super-resolution pansharpening keras tensorflow pytorch
Platform: UNKNOWN
Classifier: Development Status :: 2 - Pre-Alpha
Classifier: License :: OSI Approved :: MIT License
Classifier: Operating System :: OS Independent
Classifier: Programming Language :: Python
Classifier: Programming Language :: Python :: 3
Classifier: Programming Language :: Python :: 3.1
Classifier: Programming Language :: Python :: 3.2
Classifier: Programming Language :: Python :: 3.3
Classifier: Programming Language :: Python :: 3.4
Classifier: Programming Language :: Python :: 3.5
Classifier: Programming Language :: Python :: 3.6
Requires-Dist: numpy
Requires-Dist: opencv-python
